README.md
setup.py
macosx_tts/__init__.old.py
macosx_tts/__init__.py
macosx_tts/version.py
macosx_tts.egg-info/PKG-INFO
macosx_tts.egg-info/SOURCES.txt
macosx_tts.egg-info/dependency_links.txt
macosx_tts.egg-info/top_level.txt